svgmapper/__init__.py
svgmapper/layer.py
svgmapper/map.py
svgmapper/path.py
svgmapper/poetry.lock
svgmapper/point.py
svgmapper/symbol.py
svgmapper/translate.py
svgmapper-0.1.8.dist-info/LICENSE.txt
svgmapper-0.1.8.dist-info/METADATA
svgmapper-0.1.8.dist-info/WHEEL
svgmapper-0.1.8.dist-info/RECORD
